funapi/__init__.py
funtpp-0.0.4.dist-info/LICENSE
funtpp-0.0.4.dist-info/METADATA
funtpp-0.0.4.dist-info/WHEEL
funtpp-0.0.4.dist-info/entry_points.txt
funtpp-0.0.4.dist-info/top_level.txt
funtpp-0.0.4.dist-info/RECORD
