Metadata-Version: 2.1
Name: funtpp
Version: 0.0.4
Summary: funtpp
Home-page: https://github.com/farfarfun/funtpp
Author: bingtao
Author-email: 1007530194@qq.com
License-File: LICENSE
Requires-Dist: funpypi
Requires-Dist: funfile
Requires-Dist: requests
Requires-Dist: tqdm
